easy_queryset/__init__.py
easy_queryset/db_router.py
easy_queryset/easy_queryset.py
easy_queryset-0.0.5.dist-info/LICENSE
easy_queryset-0.0.5.dist-info/METADATA
easy_queryset-0.0.5.dist-info/WHEEL
easy_queryset-0.0.5.dist-info/top_level.txt
easy_queryset-0.0.5.dist-info/RECORD
